extractCodeBlock/__init__.py
extractCodeBlock/extract.py
extractcodeblock-0.1.0.dist-info/licenses/LICENSE
extractcodeblock-0.1.0.dist-info/METADATA
extractcodeblock-0.1.0.dist-info/WHEEL
extractcodeblock-0.1.0.dist-info/top_level.txt
extractcodeblock-0.1.0.dist-info/RECORD
