Metadata-Version: 2.4
Name: extractCodeBlock
Version: 0.1.0
Summary: A package to extract code blocks from a LLM response, enclosed in triple backticks.
Home-page: https://github.com/antick-coder/Extract_LLM_Block_Pkg.git
Author: Antick Mazumder
Author-email: antick.majumder@gmail.com
Classifier: Programming Language :: Python :: 3
Classifier: License :: OSI Approved :: MIT License
Classifier: Operating System :: OS Independent
Requires-Python: >=3.9
License-File: LICENSE
Dynamic: author
Dynamic: author-email
Dynamic: classifier
Dynamic: description
Dynamic: description-content-type
Dynamic: home-page
Dynamic: license-file
Dynamic: requires-python
Dynamic: summary
